huggingface/__init__.py
huggingface/server.py
huggingface_mcp_server-0.1.0.dist-info/licenses/LICENSE
huggingface_mcp_server-0.1.0.dist-info/METADATA
huggingface_mcp_server-0.1.0.dist-info/WHEEL
huggingface_mcp_server-0.1.0.dist-info/entry_points.txt
huggingface_mcp_server-0.1.0.dist-info/top_level.txt
huggingface_mcp_server-0.1.0.dist-info/RECORD
