Metadata-Version: 2.4
Name: huggingface-mcp-server
Version: 0.1.0
Summary: Add your description here
Requires-Python: >=3.13
License-File: LICENSE
Requires-Dist: huggingface-hub>=0.29.3
Requires-Dist: mcp>=1.5.0
Dynamic: license-file
